pyscoutnet
