Metadata-Version: 1.1
Name: PyScoutnet
Version: 2.0.0
Summary: Access to the Scoutnet.de REST-API
Home-page: https://bitbucket.org/janbrohl/pyscoutnet
Author: Jan Brohl
Author-email: janbrohl@t-online.de
License: BSD-3-Clause
Platform: UNKNOWN
Classifier: Intended Audience :: Developers
Classifier: Development Status :: 4 - Beta
Classifier: License :: OSI Approved :: BSD License
Classifier: Operating System :: OS Independent
Classifier: Programming Language :: Python
Classifier: Programming Language :: Python :: 2
Classifier: Programming Language :: Python :: 2.7
Classifier: Programming Language :: Python :: 3
Classifier: Programming Language :: Python :: 3.2
Classifier: Programming Language :: Python :: 3.3
Classifier: Programming Language :: Python :: 3.4
Classifier: Programming Language :: Python :: 3.5
Requires: requests
